04_tabla_SOP/SOP4.v
module SOP4();

// SOP del ejercicio 4

reg A, B, C, D;
  wire NA, NB, NC, ND, S1, S2, S3, S4, S5, S6, S7, S8, S9, OUT;


  not W1(NA,A);
  not W2(NB,B);
  not W3(NC,C);
  not W4(ND,D);
  or O1(S1,A,B,C,ND);
  or O2(S2,A,NB,C,D);
  or O3(S3,A,NB,C,ND);
  or O4(S4,NA,B,C,ND);
  or O5(S5,NA,B,NC,ND);
  or O6(S6,NA,NB,C,D);
  or O7(S7,NA,NB,C,ND);
  or O8(S8,NA,NB,NC,D);
  or O9(S9,NA,NB,NC,ND);
  and A1(OUT,S1,S2,S3,S4,S5,S6,S7,S8);
  

  initial begin
    $display("A B C D | Y");
    $display("------------");
    $monitor("%b %b %b %b| %b", A, B, C, D, OUT);
    A = 0; B = 0; C = 0; D = 0;
    #1 D = 1;
    #1 C = 1; D = 0;
    #1 D = 1;
    #1 B = 1; C = 0; D = 0;
    #1 D = 1;
    #1 C = 1; D = 0;
    #1 D = 1; 
    #1 A = 1; B = 0; C = 0; D = 0;
    #1 D = 1;
    #1 C = 1; D = 0;
    #1 D = 1;
    #1 B = 1; C = 0; D = 0;
    #1 D = 1;
    #1 C = 1; D = 0;
    #1 D = 1;
    #1 $finish;
  end
  

  initial 
    begin
      $dumpfile("SOP4_tb.vcd"); 
      $dumpvars(0, SOP4);
    end 

endmodule

04_tabla_SOP/SOP4_tb.vcd
$date
	Fri Jul 31 23:16:09 2020
$end
$version
	Icarus Verilog
$end
$timescale
	1ps
$end
$scope module SOP4 $end
$var wire 1 ! NA $end
$var wire 1 " NB $end
$var wire 1 # NC $end
$var wire 1 $ ND $end
$var wire 1 % OUT $end
$var wire 1 & S1 $end
$var wire 1 ' S2 $end
$var wire 1 ( S3 $end
$var wire 1 ) S4 $end
$var wire 1 * S5 $end
$var wire 1 + S6 $end
$var wire 1 , S7 $end
$var wire 1 - S8 $end
$var wire 1 . S9 $end
$var reg 1 / A $end
$var reg 1 0 B $end
$var reg 1 1 C $end
$var reg 1 2 D $end
$upscope $end
$enddefinitions $end
#0
$dumpvars
02
01
00
0/
1.
1-
1,
1+
1*
1)
1(
1'
1&
1%
1$
1#
1"
1!
$end
#1
0%
0&
0$
12
#2
1%
1$
1&
0#
02
11
#3
0$
12
#4
0%
1$
1(
0'
1#
0"
02
01
10
#5
0(
1'
0$
12
#6
1%
1$
1(
0#
02
11
#7
0$
12
#8
1%
1$
1#
1*
1)
1"
0!
02
01
00
1/
#9
0%
0)
0$
12
#10
1%
1$
1)
0#
02
11
#11
0%
0*
0$
12
#12
1$
1,
0+
1#
1*
0"
02
01
10
#13
0,
1+
0$
12
#14
0-
1$
1,
0#
02
11
#15
1%
0.
1-
0$
12
