Lab09/lab09Solucion/ej03/ej03.v
/*

Para poder hacer un Flip Flop tipo JK con un Flip Flop tipo D hay que pensar en la nube combinacional
que va a estar entre las entradas J,K y la entrada D. El diagrama  sería así:

                    Flip Flop JK                                    
        +---------------------------------+                         
        |  +--------------------------+   |                         
        |  |                          |   |                         
        |  |    +----+    +------+    |   |                         
        |  +--->|    |    |      |    |   |                         
        |       |    |    |      |    |   |                         
 J ------------>| CL |--->| D  Q |----+---|----> Q                  
        |       |    |    |      |        |                         
 K ------------>|    |    |      |        |                         
        |       +----+    +------+        |                         
        |                                 |                         
        +---------------------------------+                         

Pra construir una tabla que haga sentido tenemos que pensar en lo siguiente:
Si conozco las entradas J y K entonces sé que valor ESPERO que mi salida tenga.
J = 1 & K = 0 espero que Q = 1
J = 0 & K = 1 espero que Q = 0
J = 1 & k = 1 espero que Q = ~Q (toggle)
J = 0 & K = 0 espero que Q = Qprev (memoria)

A partir de esta lógica podemos armar la siguiente tabla:

J K Qprev | D | Q
----------|---|---
0 0   0   | 0 | 0
0 0   1   | 1 | 1
0 1   X   | 0 | 0
1 0   X   | 1 | 1
1 1   0   | 1 | 1
1 1   1   | 0 | 0

La columna Q es el valor de salida que esperamos de acuerdo a las entradas J & K.
La columna Qprev es el valor anterior del Flip Flop.
La columna D es el valor que necesitamos esté en la entrada D del Flip Flop
para que Q se cumpla.

Si quitamos la última columna (Q) obtenemos la tabla de verdad que representa
la lógica combinacional en la entrada de D.

La ecuación que representa esta tabla de verdad es:

D(Qprev, J, K) = (~Qprev * J) + (Qprev * ~K)

La representación en CircuitVerse se encuentra en el siguiente link:

https://circuitverse.org/users/20719/projects/lab09-solucion

*/

module FF_D(input clk, reset, enabled, D, output reg Q);

    always @ (posedge clk, posedge reset)
        if (reset)
            Q = 1'b0;
        else if (enabled)
            Q = D;

endmodule

module FF_JK(input clk, reset, enabled, J, K, output Q);
    
    // Solución con compuertas (estructural)
    /*
    wire notQ, notK, and1, and2, d_input;
    
    not(notQ, Q);
    not(notK, K);
    and(and1, J, notQ);
    and(and2, notK, Q);
    or(d_input, and1, and2);
    
    FF_D U1(clk, reset, enabled, d_input, Q);
    */
    // Solución con operadores
    
    FF_D U1(clk, reset, enabled, ((J & ~Q) | (~K & Q)), Q);
    
endmodule

Lab09/lab09Solucion/ej03/ej03_tb.v
module testbench();

    reg clk, reset, enabled, J, K;
    wire Q;


    FF_JK U1(clk, reset, enabled, J, K, Q);
    
    always
        #5 clk = ~clk;
        
    initial
        #150 $finish;
    
    initial begin
        $display("clk\treset\tenabled\tJ\tK\tQ");
        $monitor("%b\t%b\t%b\t%b\t%b\t%b",clk, reset, enabled, J, K, Q);
            clk = 0; reset = 0; enabled = 0; J = 0; K = 0;
        #2  reset = 1; enabled = 0; J = 0; K = 0;
        #1  reset = 0; enabled = 0; J = 0; K = 0;
        #10 reset = 0; enabled = 0; J = 1; K = 0;
        #10 reset = 0; enabled = 0; J = 1; K = 1;
        #10 reset = 0; enabled = 1; J = 1; K = 0;
        #10 reset = 0; enabled = 1; J = 0; K = 0;
        #10 reset = 0; enabled = 1; J = 0; K = 1;
        #10 reset = 0; enabled = 1; J = 0; K = 0;
        #10 reset = 0; enabled = 1; J = 1; K = 1;
        #40 reset = 0; enabled = 1; J = 1; K = 0;
        #10 reset = 0; enabled = 0; J = 0; K = 1;
    end
    
    initial begin
        $dumpfile("ej03_tb.vcd");
        $dumpvars(0, testbench);
    end

endmodule

Lab09/lab09Solucion/ej03/ej03_tb.vcd
$date
	Sat Nov 14 15:59:12 2020
$end
$version
	Icarus Verilog
$end
$timescale
	1ps
$end
$scope module testbench $end
$var wire 1 ! Q $end
$var reg 1 " J $end
$var reg 1 # K $end
$var reg 1 $ clk $end
$var reg 1 % enabled $end
$var reg 1 & reset $end
$scope module U1 $end
$var wire 1 " J $end
$var wire 1 # K $end
$var wire 1 $ clk $end
$var wire 1 % enabled $end
$var wire 1 & reset $end
$var wire 1 ! Q $end
$scope module U1 $end
$var wire 1 ' D $end
$var wire 1 $ clk $end
$var wire 1 % enabled $end
$var wire 1 & reset $end
$var reg 1 ! Q $end
$upscope $end
$upscope $end
$upscope $end
$enddefinitions $end
#0
$dumpvars
x'
0&
0%
0$
0#
0"
x!
$end
#2
0'
0!
1&
#3
0&
#5
1$
#10
0$
#13
1'
1"
#15
1$
#20
0$
#23
1#
#25
1$
#30
0$
#33
0#
1%
#35
1!
1$
#40
0$
#43
0"
#45
1$
#50
0$
#53
0'
1#
#55
0!
1$
#60
0$
#63
0#
#65
1$
#70
0$
#73
1'
1#
1"
#75
0'
1!
1$
#80
0$
#85
1'
0!
1$
#90
0$
#95
0'
1!
1$
#100
0$
#105
1'
0!
1$
#110
0$
#113
0#
#115
1!
1$
#120
0$
#123
0'
1#
0"
0%
