03_tabla_SOP/SOP3.v
module SOP3();

// SOP del ejercicio 3

reg A, B, C, D;
  wire NA, NB, NC, ND, S1, S2, S3, S4, S5, S6, S7, S8, OUT;


  not W1(NA,A);
  not W2(NB,B);
  not W3(NC,C);
  not W4(ND,D);
  or O1(S1,A,NB,C,D);
  or O2(S2,A,NB,C,ND);
  or O3(S3,A,NB,NC,D);
  or O4(S4,A,NB,NC,ND);
  or O5(S5,NA,B,C,ND);
  or O6(S6,NA,NB,NC,ND);
  or O7(S7,NA,NB,C,D);
  or O8(S8,NA,NB,C,ND);
  and A1(OUT,S1,S2,S3,S4,S5,S6,S7,S8);
  

  initial begin
    $display("A B C D | Y");
    $display("------------");
    $monitor("%b %b %b %b| %b", A, B, C, D, OUT);
    A = 0; B = 0; C = 0; D = 0;
    #1 D = 1;
    #1 C = 1; D = 0;
    #1 D = 1;
    #1 B = 1; C = 0; D = 0;
    #1 D = 1;
    #1 C = 1; D = 0;
    #1 D = 1; 
    #1 A = 1; B = 0; C = 0; D = 0;
    #1 D = 1;
    #1 C = 1; D = 0;
    #1 D = 1;
    #1 B = 1; C = 0; D = 0;
    #1 D = 1;
    #1 C = 1; D = 0;
    #1 D = 1;
    #1 $finish;
  end
  

  initial 
    begin
      $dumpfile("SOP3_tb.vcd"); 
      $dumpvars(0, SOP3);
    end 

endmodule

03_tabla_SOP/SOP3_tb.vcd
$date
	Fri Jul 31 22:57:55 2020
$end
$version
	Icarus Verilog
$end
$timescale
	1ps
$end
$scope module SOP3 $end
$var wire 1 ! NA $end
$var wire 1 " NB $end
$var wire 1 # NC $end
$var wire 1 $ ND $end
$var wire 1 % OUT $end
$var wire 1 & S1 $end
$var wire 1 ' S2 $end
$var wire 1 ( S3 $end
$var wire 1 ) S4 $end
$var wire 1 * S5 $end
$var wire 1 + S6 $end
$var wire 1 , S7 $end
$var wire 1 - S8 $end
$var reg 1 . A $end
$var reg 1 / B $end
$var reg 1 0 C $end
$var reg 1 1 D $end
$upscope $end
$enddefinitions $end
#0
$dumpvars
01
00
0/
0.
1-
1,
1+
1*
1)
1(
1'
1&
1%
1$
1#
1"
1!
$end
#1
0$
11
#2
1$
0#
01
10
#3
0$
11
#4
0%
1$
1'
0&
1#
0"
01
00
1/
#5
0'
1&
0$
11
#6
0(
1$
1'
0#
01
10
#7
0)
1(
0$
11
#8
1%
1$
1#
1*
1"
1)
0!
01
00
0/
1.
#9
0%
0*
0$
11
#10
1%
1$
1*
0#
01
10
#11
0$
11
#12
0%
1$
1-
0,
1#
0"
01
00
1/
#13
0-
1,
0$
11
#14
1%
1$
1-
0#
01
10
#15
0%
0+
0$
11
