03_tabla_POS/POS3.v
module POS3();

// POS del ejercicio 3

reg A, B, C, D;
  wire NA, NB, NC, ND, M1, M2, M3, M4, M5, M6, M7, OUT;


  not W1(NA,A);
  not W2(NB,B);
  not W3(NC,C);
  not W4(ND,D);
  and A1(M1,NA,NB,NC,ND);
  and A2(M2,NA,NB,NC,D);
  and A3(M3,NA,NB,C,ND);
  and A4(M4,NA,NB,C,D);
  and A5(M5,A,NB,NC,ND);
  and A6(M6,A,NB,C,ND);
  and A7(M7,A,B,C,ND);
  or O1(OUT,M1,M2,M3,M4,M5,M6,M7);

  initial begin
    $display("A B C D | Y");
    $display("------------");
    $monitor("%b %b %b %b| %b", A, B, C, D, OUT);
    A = 0; B = 0; C = 0; D = 0;
    #1 D = 1;
    #1 C = 1; D = 0;
    #1 D = 1;
    #1 B = 1; C = 0; D = 0;
    #1 D = 1;
    #1 C = 1; D = 0;
    #1 D = 1; 
    #1 A = 1; B = 0; C = 0; D = 0;
    #1 D = 1;
    #1 C = 1; D = 0;
    #1 D = 1;
    #1 B = 1; C = 0; D = 0;
    #1 D = 1;
    #1 C = 1; D = 0;
    #1 D = 1;
    #1 $finish;
  end
  

  initial 
    begin
      $dumpfile("POS3_tb.vcd"); 
      $dumpvars(0, POS3);
    end 

endmodule

03_tabla_POS/POS3_tb.vcd
$date
	Fri Jul 31 22:36:31 2020
$end
$version
	Icarus Verilog
$end
$timescale
	1ps
$end
$scope module POS3 $end
$var wire 1 ! M1 $end
$var wire 1 " M2 $end
$var wire 1 # M3 $end
$var wire 1 $ M4 $end
$var wire 1 % M5 $end
$var wire 1 & M6 $end
$var wire 1 ' M7 $end
$var wire 1 ( NA $end
$var wire 1 ) NB $end
$var wire 1 * NC $end
$var wire 1 + ND $end
$var wire 1 , OUT $end
$var reg 1 - A $end
$var reg 1 . B $end
$var reg 1 / C $end
$var reg 1 0 D $end
$upscope $end
$enddefinitions $end
#0
$dumpvars
00
0/
0.
0-
1,
1+
1*
1)
1(
0'
0&
0%
0$
0#
0"
1!
$end
#1
0!
1"
0+
10
#2
1#
0"
1+
0*
00
1/
#3
0#
1$
0+
10
#4
0,
1+
0$
1*
0)
00
0/
1.
#5
0+
10
#6
1+
0*
00
1/
#7
0+
10
#8
1,
1%
1+
1*
1)
0(
00
0/
0.
1-
#9
0,
0%
0+
10
#10
1,
1&
1+
0*
00
1/
#11
0,
0&
0+
10
#12
1+
1*
0)
00
0/
1.
#13
0+
10
#14
1,
1'
1+
0*
00
1/
#15
0,
0'
0+
10
