02_tabla_POS/POS2.v
module POS2();

// POS del ejrcicio 2

reg A, B, C;
  wire NA, NB, NC, M1, M2, M3, OUT;


  not W1(NA,A);
  not W2(NB,B);
  not W3(NC,C);
  and A1(M1,NA,NB,C); 
  and A2(M2,A,B,NC);
  and A3(M3,A,B,C);
  or O1(OUT,M1,M2,M3);

  initial begin
    $display("A B C | Y");
    $display("-------");
    $monitor("%b %b %b | %b", A, B, C, OUT);
    A = 0; B = 0; C = 0;
    #1 C = 1;
    #1 B = 1; C = 0;
    #1 C = 1; 
    #1 A = 1; B = 0; C = 0;
    #1 C = 1;
    #1 B = 1; C = 0;
    #1 C = 1;
    #1 $finish;
  end
  

  initial 
    begin
      $dumpfile("POS2_tb.vcd"); 
      $dumpvars(0, POS2);
    end 

endmodule

02_tabla_POS/POS2_tb.vcd
$date
	Fri Jul 31 21:23:51 2020
$end
$version
	Icarus Verilog
$end
$timescale
	1ps
$end
$scope module POS2 $end
$var wire 1 ! M1 $end
$var wire 1 " M2 $end
$var wire 1 # M3 $end
$var wire 1 $ NA $end
$var wire 1 % NB $end
$var wire 1 & NC $end
$var wire 1 ' OUT $end
$var reg 1 ( A $end
$var reg 1 ) B $end
$var reg 1 * C $end
$upscope $end
$enddefinitions $end
#0
$dumpvars
0*
0)
0(
0'
1&
1%
1$
0#
0"
0!
$end
#1
1'
1!
0&
1*
#2
0'
0!
1&
0%
0*
1)
#3
0&
1*
#4
1&
1%
0$
0*
0)
1(
#5
0&
1*
#6
1'
1"
1&
0%
0*
1)
#7
0"
1#
0&
1*
