Lab4/Verilog/OPERADORES LÓGICOS/LOGICOS.v
module LOGICOS1(input wire A, B, C, output wire Y);

// ECUACIÓN A IMPLEMENTAR: B' 1.2

  not W2(Y,B);

endmodule	

module LOGICOS2(input wire A, B, C,D, output wire Y);

// ECUACIÓN A IMPLEMENTAR: B'+C 2.2

  not W2(NB,B);

  or O1(Y,NB,C);

endmodule

module LOGICOS3(input wire A, B, C, output wire Y);

// ECUACIÓN A IMPLEMENTAR: AD+B+C'D 2.3

  not W3(NC,C);

  and A1(S1,A,D);
  and A2(S2,NC,D);
  or O1(Y,S1,B,S2);

endmodule

module LOGICOS4(input wire A, B, C, output wire Y);

// ECUACIÓN A IMPLEMENTAR: B+A'C'

  not W1(NA,A);
  not W3(NC,C);

  and A1(S1,NA,NC);
  or O1(Y,S1,B);

endmodule

Lab4/Verilog/OPERADORES LÓGICOS/LOGICOS_tb.v
module testbench();

  reg P1, P2, P3, P4;
  wire Y1, Y2, Y3, Y4;

  LOGICOS1 L1(P1, P2, P3, Y1);
  LOGICOS2 L2(P1, P2, P3, P4, Y2);
  LOGICOS3 L3(P1, P2, P3, Y3);
  LOGICOS4 L4(P1, P2, P3, Y4);

  initial begin
    $display("A B C | Y");
    $display("-------");
    $monitor("%b %b %b | %b", P1, P2, P3, Y1);
    P1 = 0; P2 = 0; P3 = 0;
    #1 P3 = 1;
    #1 P2 = 1; P3 = 0;
    #1 P3 = 1; 
    #1 P1 = 1; P2 = 0; P3 = 0;
    #1 P3 = 1;
    #1 P2 = 1; P3 = 0;
    #1 P3 = 1;
  end

  initial begin
    #8 
    $display("\n\n");
    $display("A B C D | Y");
    $display("------------");
    $monitor("%b %b %b %b | %b", P1, P2, P3, P4, Y2);
    P1 = 0; P2 = 0; P3 = 0; P4 = 0;
    #1 P4 = 1;
    #1 P3 = 1; P4 = 0;
    #1 P4 = 1;
    #1 P2 = 1; P3 = 0; P4 = 0;
    #1 P4 = 1;
    #1 P3 = 1; P4 = 0;
    #1 P4 = 1; 
    #1 P1 = 1; P2 = 0; P3 = 0; P4 = 0;
    #1 P4 = 1;
    #1 P3 = 1; P4 = 0;
    #1 P4 = 1;
    #1 P2 = 1; P3 = 0; P4 = 0;
    #1 P4 = 1;
    #1 P3 = 1; P4 = 0;
    #1 P4 = 1;
  end
  
initial begin
    #25 
    $display("\n\n");
    $display("A B C | Y");
    $display("-------");
    $monitor("%b %b %b | %b", P1, P2, P3, Y3);
    P1 = 0; P2 = 0; P3 = 0;
    #1 P3 = 1;
    #1 P2 = 1; P3 = 0;
    #1 P3 = 1; 
    #1 P1 = 1; P2 = 0; P3 = 0;
    #1 P3 = 1;
    #1 P2 = 1; P3 = 0;
    #1 P3 = 1;
  end
initial begin
    #33 
    $display("\n\n");
    $display("A B C | Y");
    $display("-------");
    $monitor("%b %b %b | %b", P1, P2, P3, Y4);
    P1 = 0; P2 = 0; P3 = 0;
    #1 P3 = 1;
    #1 P2 = 1; P3 = 0;
    #1 P3 = 1; 
    #1 P1 = 1; P2 = 0; P3 = 0;
    #1 P3 = 1;
    #1 P2 = 1; P3 = 0;
    #1 P3 = 1;
    #1 $finish;
  end


  initial begin
      $dumpfile("LOGICOS_tb.vcd"); 
      $dumpvars(0, testbench);

  end
endmodule

Lab4/Verilog/OPERADORES LÓGICOS/LOGICOS_tb.vcd
$date
	Sun Aug 09 11:26:03 2020
$end
$version
	Icarus Verilog
$end
$timescale
	1ps
$end
$scope module testbench $end
$var wire 1 ! Y4 $end
$var wire 1 " Y3 $end
$var wire 1 # Y2 $end
$var wire 1 $ Y1 $end
$var reg 1 % P1 $end
$var reg 1 & P2 $end
$var reg 1 ' P3 $end
$var reg 1 ( P4 $end
$scope module L1 $end
$var wire 1 % A $end
$var wire 1 & B $end
$var wire 1 ' C $end
$var wire 1 $ Y $end
$upscope $end
$scope module L2 $end
$var wire 1 % A $end
$var wire 1 & B $end
$var wire 1 ' C $end
$var wire 1 ( D $end
$var wire 1 ) NB $end
$var wire 1 # Y $end
$upscope $end
$scope module L3 $end
$var wire 1 % A $end
$var wire 1 & B $end
$var wire 1 ' C $end
$var wire 1 * D $end
$var wire 1 + NC $end
$var wire 1 , S1 $end
$var wire 1 - S2 $end
$var wire 1 " Y $end
$upscope $end
$scope module L4 $end
$var wire 1 % A $end
$var wire 1 & B $end
$var wire 1 ' C $end
$var wire 1 . NA $end
$var wire 1 / NC $end
$var wire 1 0 S1 $end
$var wire 1 ! Y $end
$upscope $end
$upscope $end
$enddefinitions $end
#0
$dumpvars
10
1/
1.
x-
0,
1+
z*
1)
x(
0'
0&
0%
1$
1#
x"
1!
$end
#1
0"
0!
0-
00
0+
0/
1'
#2
x-
10
0#
1+
1/
0$
0)
1"
1!
0'
1&
#3
0-
00
1#
0+
0/
1'
#4
x-
1+
1/
1$
1)
x"
0!
x,
0.
0'
0&
1%
#5
0-
0+
0/
1'
#6
x-
0#
1+
1/
0$
0)
1"
1!
0'
1&
#7
0-
1#
0+
0/
1'
#8
x-
10
1+
1/
1$
1)
x"
1!
0,
1.
0(
0'
0&
0%
#9
1(
#10
0"
0!
0-
00
0+
0/
0(
1'
#11
1(
#12
x-
10
0#
1+
1/
0$
0)
1"
1!
0(
0'
1&
#13
1(
#14
0-
00
1#
0+
0/
0(
1'
#15
1(
#16
x-
1+
1/
1$
1)
x"
0!
x,
0.
0(
0'
0&
1%
#17
1(
#18
0-
0+
0/
0(
1'
#19
1(
#20
x-
0#
1+
1/
0$
0)
1"
1!
0(
0'
1&
#21
1(
#22
0-
1#
0+
0/
0(
1'
#23
1(
#25
x-
10
1+
1/
1$
1)
x"
1!
0,
1.
0'
0&
0%
#26
0"
0!
0-
00
0+
0/
1'
#27
x-
10
0#
1+
1/
0$
0)
1"
1!
0'
1&
#28
0-
00
1#
0+
0/
1'
#29
x-
1+
1/
1$
1)
x"
0!
x,
0.
0'
0&
1%
#30
0-
0+
0/
1'
#31
x-
0#
1+
1/
0$
0)
1"
1!
0'
1&
#32
0-
1#
0+
0/
1'
#33
x-
10
1+
1/
1$
1)
x"
1!
0,
1.
0'
0&
0%
#34
0"
0!
0-
00
0+
0/
1'
#35
x-
10
0#
1+
1/
0$
0)
1"
1!
0'
1&
#36
0-
00
1#
0+
0/
1'
#37
x-
1+
1/
1$
1)
x"
0!
x,
0.
0'
0&
1%
#38
0-
0+
0/
1'
#39
x-
0#
1+
1/
0$
0)
1"
1!
0'
1&
#40
0-
1#
0+
0/
1'
