Lab09/lab09Solucion/ej01/ej01.v
module FF_D(input clk, reset, enabled, D, output reg Q);

    always @ (posedge clk, posedge reset)
        if (reset)
            Q = 1'b0;
        else if (enabled)
            Q = D;

endmodule


module FF_D_2(input clk, reset, enabled, input [1:0] D, output [1:0] Q);

    FF_D U1 (clk, reset, enabled, D[1], Q[1]);
    FF_D U0 (.clk(clk), .reset(reset), .enabled(enabled), .D(D[0]), .Q(Q[0]));

endmodule


module FF_D_4(input clk, reset, enabled, input [3:0] D, output [3:0] Q);

    FF_D U2 (clk, reset, enabled, D[3], Q[3]);
    FF_D U3 (.enabled(enabled), .D(D[2]), .clk(clk), .Q(Q[2]), .reset(reset));
    FF_D U1 (clk, reset, enabled, D[1], Q[1]);
    FF_D U0 (.clk(clk), .reset(reset), .enabled(enabled), .D(D[0]), .Q(Q[0]));

endmodule

Lab09/lab09Solucion/ej01/ej01_tb.v
module testbench();

    reg clk, reset, enabled, D1;
    wire Q1;
    reg [1:0] D2;
    wire [1:0] Q2;
    reg [3:0] D3;
    wire [3:0] Q3;

    FF_D U1(clk, reset, enabled, D1, Q1);
    FF_D_2 U2(clk, reset, enabled, D2, Q2);
    FF_D_4 U3(clk, reset, enabled, D3, Q3);
    
    always
        #5 clk = ~clk;
        
    initial
        #60 $finish;
    
    initial begin
        $display("clk\treset\tenabled\tD1\tQ1\tD2\tQ2\tD3\tQ3");
        $monitor("%b\t%b\t%b\t%b\t%b\t%b\t%b\t%b\t%b", clk, reset, enabled, D1, Q1, D2, Q2, D3, Q3);
            clk = 0; reset = 0; enabled = 0; D1 = 0; D2 = 2'b00; D3 = 4'b0000;
        #1  reset = 1; enabled = 0; D1 = 0; D2 = 2'b00; D3 = 4'b0000;
        #1  reset = 0; enabled = 0; D1 = 1; D2 = 2'b11; D3 = 4'b1111;
        #10 enabled = 1; D1 = 1; D2 = 2'b11; D3 = 4'b1111;
        #10 enabled = 0; D1 = 0; D2 = 2'b10; D3 = 4'b1010;
        #10 enabled = 1;
        #10 enabled = 1; D1 = 1; D2 = 2'b01; D3 = 4'b0101;
    end
    
    initial begin
        $dumpfile("ej01_tb.vcd");
        $dumpvars(0, testbench);
    end

endmodule

Lab09/lab09Solucion/ej01/ej01_tb.vcd
$date
	Sat Nov 14 10:29:18 2020
$end
$version
	Icarus Verilog
$end
$timescale
	1ps
$end
$scope module testbench $end
$var wire 4 ! Q3 [3:0] $end
$var wire 2 " Q2 [1:0] $end
$var wire 1 # Q1 $end
$var reg 1 $ D1 $end
$var reg 2 % D2 [1:0] $end
$var reg 4 & D3 [3:0] $end
$var reg 1 ' clk $end
$var reg 1 ( enabled $end
$var reg 1 ) reset $end
$scope module U1 $end
$var wire 1 $ D $end
$var wire 1 ' clk $end
$var wire 1 ( enabled $end
$var wire 1 ) reset $end
$var reg 1 # Q $end
$upscope $end
$scope module U2 $end
$var wire 2 * D [1:0] $end
$var wire 1 ' clk $end
$var wire 1 ( enabled $end
$var wire 1 ) reset $end
$var wire 2 + Q [1:0] $end
$scope module U0 $end
$var wire 1 , D $end
$var wire 1 ' clk $end
$var wire 1 ( enabled $end
$var wire 1 ) reset $end
$var reg 1 - Q $end
$upscope $end
$scope module U1 $end
$var wire 1 . D $end
$var wire 1 ' clk $end
$var wire 1 ( enabled $end
$var wire 1 ) reset $end
$var reg 1 / Q $end
$upscope $end
$upscope $end
$scope module U3 $end
$var wire 4 0 D [3:0] $end
$var wire 1 ' clk $end
$var wire 1 ( enabled $end
$var wire 1 ) reset $end
$var wire 4 1 Q [3:0] $end
$scope module U0 $end
$var wire 1 2 D $end
$var wire 1 ' clk $end
$var wire 1 ( enabled $end
$var wire 1 ) reset $end
$var reg 1 3 Q $end
$upscope $end
$scope module U1 $end
$var wire 1 4 D $end
$var wire 1 ' clk $end
$var wire 1 ( enabled $end
$var wire 1 ) reset $end
$var reg 1 5 Q $end
$upscope $end
$scope module U2 $end
$var wire 1 6 D $end
$var wire 1 ' clk $end
$var wire 1 ( enabled $end
$var wire 1 ) reset $end
$var reg 1 7 Q $end
$upscope $end
$scope module U3 $end
$var wire 1 8 D $end
$var wire 1 ' clk $end
$var wire 1 ( enabled $end
$var wire 1 ) reset $end
$var reg 1 9 Q $end
$upscope $end
$upscope $end
$upscope $end
$enddefinitions $end
#0
$dumpvars
x9
08
x7
06
x5
04
x3
02
bx 1
b0 0
x/
0.
x-
0,
bx +
b0 *
0)
0(
0'
b0 &
b0 %
0$
x#
bx "
bx !
$end
#1
0#
0/
b0 "
b0 +
0-
07
09
05
b0 !
b0 1
03
1)
#2
16
18
14
12
1.
1,
b1111 &
b1111 0
b11 %
b11 *
1$
0)
#5
1'
#10
0'
#12
1(
#15
1#
1/
b11 "
b11 +
1-
17
19
15
b1111 !
b1111 1
13
1'
#20
0'
#22
08
02
0,
b1010 &
b1010 0
b10 %
b10 *
0$
0(
#25
1'
#30
0'
#32
1(
#35
0#
b10 "
b10 +
0-
09
b1010 !
b1010 1
03
1'
#40
0'
#42
06
18
04
12
0.
1,
b101 &
b101 0
b1 %
b1 *
1$
#45
13
05
19
b101 !
b101 1
07
1-
b1 "
b1 +
0/
1#
1'
